MANIFEST.in
README.rst
setup.cfg
setup.py
conf/__init__.py
conf/admin.cfg
conf/publishers/eventlet.cfg
conf/publishers/fapws3.cfg
conf/publishers/fastcgi.cfg
conf/publishers/lighttpd.cfg
conf/publishers/memcache.cfg
data/__init__.py
doc/Makefile
doc/application_creation.txt
doc/callbacks_forms.txt
doc/changelog.txt
doc/components.txt
doc/conf.py
doc/configuration_file.txt
doc/database.txt
doc/demo_installation.txt
doc/demo_upgrade.txt
doc/deployment.txt
doc/description.txt
doc/entry_points.txt
doc/features.txt
doc/framework_installation.txt
doc/framework_upgrade.txt
doc/i18n.txt
doc/index.txt
doc/license.txt
doc/log.txt
doc/mailing_lists.txt
doc/make.bat
doc/nagare-admin.txt
doc/object_references.txt
doc/presentation.txt
doc/publisher_file.txt
doc/quickstart.txt
doc/renderer.txt
doc/restful.txt
doc/third_party.txt
doc/tutorial1.txt
doc/tutorial2.txt
doc/tutorial3.txt
doc/tutorial4.txt
doc/wiki_tutorial.txt
doc/wsgiapp.txt
doc/_static/distth___-webfont.eot
doc/_static/distth___-webfont.ttf
doc/_static/favicon.ico
doc/_static/logo.png
doc/_static/theme.css
doc/img/banner.png
doc/img/tutorial1.png
doc/source/nagare.admin.interface.txt
doc/source/nagare.admin.txt
doc/source/nagare.namespaces.test.txt
doc/source/nagare.namespaces.txt
doc/source/nagare.publishers.txt
doc/source/nagare.security.txt
doc/source/nagare.sessions.txt
doc/source/nagare.test.txt
doc/source/nagare.txt
nagare/__init__.py
nagare/ajax.py
nagare/callbacks.py
nagare/comet.py
nagare/component.py
nagare/config.py
nagare/continuation.py
nagare/database.py
nagare/editor.py
nagare/i18n.py
nagare/local.py
nagare/log.py
nagare/partial.py
nagare/presentation.py
nagare/pyjs.py
nagare/serializer.py
nagare/state.py
nagare/top.py
nagare/util.py
nagare/validator.py
nagare/var.py
nagare/wsgi.py
nagare.egg-info/PKG-INFO
nagare.egg-info/SOURCES.txt
nagare.egg-info/dependency_links.txt
nagare.egg-info/entry_points.txt
nagare.egg-info/namespace_packages.txt
nagare.egg-info/not-zip-safe
nagare.egg-info/requires.txt
nagare.egg-info/top_level.txt
nagare/admin/__init__.py
nagare/admin/admin_app.py
nagare/admin/command.py
nagare/admin/create.py
nagare/admin/create_rules.py
nagare/admin/db.py
nagare/admin/info.py
nagare/admin/reference.py
nagare/admin/reloader.py
